promptantic/__init__.py
promptantic/completers.py
promptantic/creator.py
promptantic/exceptions.py
promptantic/generator.py
promptantic/handlers/__init__.py
promptantic/handlers/base.py
promptantic/handlers/constrained.py
promptantic/handlers/date_time.py
promptantic/handlers/enums.py
promptantic/handlers/literal.py
promptantic/handlers/models.py
promptantic/handlers/network.py
promptantic/handlers/primitives.py
promptantic/handlers/sequences.py
promptantic/handlers/special.py
promptantic/handlers/stdlib.py
promptantic/handlers/unions.py
promptantic/py.typed
promptantic/type_utils.py
promptantic/ui/__init__.py
promptantic/ui/formatting.py
promptantic/ui/style.py
promptantic/utils/__init__.py
promptantic-1.0.0.dist-info/WHEEL
promptantic-1.0.0.dist-info/METADATA
promptantic-1.0.0.dist-info/RECORD
