Metadata-Version: 2.3
Name: promptantic
Version: 1.0.0
Summary: Generate pydantic models using prompts
Keywords: 
Author: Philipp Temminghoff
Author-email: Philipp Temminghoff <philipptemminghoff@googlemail.com>
License: MIT License
Classifier: Development Status :: 4 - Beta
Classifier: Framework :: Pydantic
Classifier: Framework :: Pydantic :: 2
Classifier: Intended Audience :: Developers
Classifier: Operating System :: OS Independent
Classifier: Programming Language :: Python :: 3
Classifier: Programming Language :: Python :: 3 :: Only
Classifier: Programming Language :: Python :: 3.12
Classifier: Programming Language :: Python :: 3.13
Classifier: Programming Language :: Python :: 3.14
Classifier: Topic :: Documentation
Classifier: Topic :: Software Development
Classifier: Topic :: Utilities
Classifier: Typing :: Typed
Requires-Dist: prompt-toolkit>=3.0.48
Requires-Dist: pydantic
Requires-Dist: schemez
Requires-Dist: universal-pathlib>=0.3.0
Requires-Python: >=3.13
Project-URL: Code coverage, https://app.codecov.io/gh/phil65/promptantic
Project-URL: Discussions, https://github.com/phil65/promptantic/discussions
Project-URL: Documentation, https://phil65.github.io/promptantic/
Project-URL: Issues, https://github.com/phil65/promptantic/issues
Project-URL: Source, https://github.com/phil65/promptantic
